django_pudb.py
django_pudb-0.1.0.dist-info/top_level.txt
django_pudb-0.1.0.dist-info/METADATA
django_pudb-0.1.0.dist-info/DESCRIPTION.rst
django_pudb-0.1.0.dist-info/metadata.json
django_pudb-0.1.0.dist-info/WHEEL
django_pudb-0.1.0.dist-info/RECORD
